berglas_python.py
berglas_python-0.3.4.dist-info/LICENSE
berglas_python-0.3.4.dist-info/METADATA
berglas_python-0.3.4.dist-info/WHEEL
berglas_python-0.3.4.dist-info/top_level.txt
berglas_python-0.3.4.dist-info/RECORD
