Metadata-Version: 2.1
Name: berglas-python
Version: 0.3.4
Summary: Decipher the Berglas keys
Home-page: https://github.com/guillaumeblaquiere/berglas-python
Author: Guillaume Blaquiere
Author-email: guillaume.blaquiere@gmail.com
License: Apache 2.0
Platform: UNKNOWN
Classifier: Programming Language :: Python :: 3
Classifier: License :: OSI Approved :: Apache Software License
Classifier: Operating System :: OS Independent
Requires-Dist: google-cloud-storage
Requires-Dist: google-cloud-kms
Requires-Dist: cryptography
